Orange3_Associate_zh-1.1.6-py3.7-nspkg.pth
orangecontrib/associate/__init__.py
orangecontrib/associate/_fpgrowth.cpython-37m-darwin.so
orangecontrib/associate/_fpgrowth.pyx
orangecontrib/associate/fpgrowth.py
orangecontrib/associate/widgets/__init__.py
orangecontrib/associate/widgets/owassociate.py
orangecontrib/associate/widgets/owitemsets.py
orangecontrib/associate/widgets/icons/AssociationRules.svg
orangecontrib/associate/widgets/icons/FrequentItemsets.svg
Orange3_Associate_zh-1.1.6.dist-info/METADATA
Orange3_Associate_zh-1.1.6.dist-info/WHEEL
Orange3_Associate_zh-1.1.6.dist-info/entry_points.txt
Orange3_Associate_zh-1.1.6.dist-info/namespace_packages.txt
Orange3_Associate_zh-1.1.6.dist-info/top_level.txt
Orange3_Associate_zh-1.1.6.dist-info/RECORD
