Metadata-Version: 2.1
Name: Orange3-Associate-zh
Version: 1.1.6
Summary: Orange add-on for mining frequent itemsets and association rules.
Home-page: https://github.com/biolab/orange3-associate
Author: Bioinformatics Laboratory, FRI UL
Author-email: info@biolab.si
License: UNKNOWN
Keywords: frequent itemset mining,frequent pattern mining,association rules,apriori,fp-growth,frequent patterns,FIM,FPM,orange3 add-on
Platform: UNKNOWN
Classifier: Programming Language :: Python
Classifier: License :: OSI Approved :: GNU General Public License v3 or later (GPLv3+)
Classifier: Operating System :: OS Independent
Classifier: Topic :: Scientific/Engineering :: Artificial Intelligence
Classifier: Topic :: Software Development :: Libraries :: Python Modules
Classifier: Intended Audience :: Education
Classifier: Intended Audience :: Science/Research
Classifier: Intended Audience :: Developers
Requires-Dist: numpy
Requires-Dist: scipy
